<?xml version='1.1' encoding='UTF-8'?>
<flow-definition plugin="workflow-job@2.36">
  <actions>
    <org.jenkinsci.plugins.pipeline.modeldefinition.actions.DeclarativeJobAction plugin="pipeline-model-definition@1.5.1"/>
    <org.jenkinsci.plugins.pipeline.modeldefinition.actions.DeclarativeJobPropertyTrackerAction plugin="pipeline-model-definition@1.5.1">
      <jobProperties/>
      <triggers/>
      <parameters/>
      <options/>
    </org.jenkinsci.plugins.pipeline.modeldefinition.actions.DeclarativeJobPropertyTrackerAction>
  </actions>
  <description></description>
  <keepDependencies>false</keepDependencies>
  <properties>
    <hudson.model.ParametersDefinitionProperty>
      <parameterDefinitions>
        <hudson.model.StringParameterDefinition>
          <name>branchName</name>
          <description></description>
          <defaultValue>master</defaultValue>
          <trim>false</trim>
        </hudson.model.StringParameterDefinition>
        <hudson.model.StringParameterDefinition>
          <name>repositoryName</name>
          <description></description>
          <defaultValue></defaultValue>
          <trim>false</trim>
        </hudson.model.StringParameterDefinition>
        <hudson.model.StringParameterDefinition>
          <name>repositoryUrl</name>
          <description></description>
          <defaultValue></defaultValue>
          <trim>false</trim>
        </hudson.model.StringParameterDefinition>
      </parameterDefinitions>
    </hudson.model.ParametersDefinitionProperty>
  </properties>
  <definition class="org.jenkinsci.plugins.workflow.cps.CpsFlowDefinition" plugin="workflow-cps@2.80">
    <script>pipeline {
   agent any

   stages {
      stage(&apos;branch name&apos;) {
         steps {
            echo &quot;${params.branchName}&quot;
         }
      }
      stage(&apos;repository&apos;) {
         steps {
            echo &quot;${params.repositoryName}&quot;
            echo &quot;${params.repositoryUrl}&quot;
         }
      }
   }
}
</script>
    <sandbox>true</sandbox>
  </definition>
  <triggers/>
  <authToken>hoge</authToken>
  <disabled>false</disabled>
</flow-definition>